opg_circleci/__init__.py
opg_circleci/cancel_redundant_builds.py
opg_circleci-0.0.3.dist-info/LICENSE
opg_circleci-0.0.3.dist-info/METADATA
opg_circleci-0.0.3.dist-info/WHEEL
opg_circleci-0.0.3.dist-info/top_level.txt
opg_circleci-0.0.3.dist-info/RECORD
