Metadata-Version: 2.1
Name: opg-circleci
Version: 0.0.3
Summary: Shared Integrations Code
Home-page: https://github.com/ministryofjustice/opg-data
Author: OPG
Author-email: opg-integrations@digital.justice.gov.uk
License: UNKNOWN
Platform: UNKNOWN
Classifier: Programming Language :: Python :: 3
Classifier: License :: OSI Approved :: MIT License
Classifier: Operating System :: OS Independent
Requires-Python: >=3.7
License-File: LICENSE
